LICENSE
MANIFEST.in
NOTICE
README.md
pyproject.toml
requirements.txt
setup.cfg
setup.py
benchmarks/__init__.py
benchmarks/fsdp.py
benchmarks/moe.py
benchmarks/oss.py
benchmarks/pipe.py
benchmarks/utils.py
benchmarks/datasets/__init__.py
benchmarks/datasets/mnist.py
benchmarks/datasets/wikitext2_data.py
benchmarks/golden_configs/__init__.py
benchmarks/golden_configs/lm_wikitext2.py
benchmarks/golden_configs/oss_mnist.py
benchmarks/models/__init__.py
benchmarks/models/transformer_lm.py
fairscale/__init__.py
fairscale/version.py
fairscale.egg-info/PKG-INFO
fairscale.egg-info/SOURCES.txt
fairscale.egg-info/dependency_links.txt
fairscale.egg-info/entry_points.txt
fairscale.egg-info/requires.txt
fairscale.egg-info/top_level.txt
fairscale/clib/fused_adam_cuda/compat.h
fairscale/clib/fused_adam_cuda/multi_tensor_apply.cuh
fairscale/experimental/__init__.py
fairscale/experimental/nn/__init__.py
fairscale/experimental/nn/auto_shard.py
fairscale/experimental/nn/mevo.py
fairscale/experimental/nn/offload.py
fairscale/experimental/nn/sync_batchnorm.py
fairscale/experimental/nn/ampnet_pipe/__init__.py
fairscale/experimental/nn/ampnet_pipe/ampnet.py
fairscale/experimental/nn/ampnet_pipe/pipe.py
fairscale/experimental/nn/data_parallel/__init__.py
fairscale/experimental/nn/data_parallel/gossip/__init__.py
fairscale/experimental/nn/data_parallel/gossip/distributed.py
fairscale/experimental/nn/data_parallel/gossip/gossiper.py
fairscale/experimental/nn/data_parallel/gossip/graph_manager.py
fairscale/experimental/nn/data_parallel/gossip/mixing_manager.py
fairscale/experimental/nn/data_parallel/gossip/utils/__init__.py
fairscale/experimental/nn/data_parallel/gossip/utils/cuda_metering.py
fairscale/experimental/nn/data_parallel/gossip/utils/helpers.py
fairscale/experimental/nn/distributed_pipeline/__init__.py
fairscale/experimental/nn/distributed_pipeline/data.py
fairscale/experimental/nn/distributed_pipeline/graph.py
fairscale/experimental/nn/distributed_pipeline/loss.py
fairscale/experimental/nn/distributed_pipeline/partition_handler.py
fairscale/experimental/nn/distributed_pipeline/pipeline.py
fairscale/experimental/nn/distributed_pipeline/trace.py
