Metadata-Version: 2.1
Name: fairscale
Version: 0.4.11
Summary: FairScale: A PyTorch library for large-scale and high-performance training.
Home-page: UNKNOWN
Author: Foundational AI Research @ Meta AI
Author-email: todo@fb.com
License: UNKNOWN
Platform: UNKNOWN
Classifier: Programming Language :: Python :: 3.8
Classifier: Programming Language :: Python :: 3.9
Classifier: Programming Language :: Python :: 3.10
Classifier: License :: OSI Approved :: BSD License
Classifier: Topic :: Scientific/Engineering :: Artificial Intelligence
Classifier: Operating System :: OS Independent
Requires-Python: >=3.8
License-File: LICENSE
License-File: NOTICE
